runweb-0.4.1.dist-info/METADATA
runweb-0.4.1.dist-info/WHEEL
runweb-0.4.1.dist-info/entry_points.txt
runweb-0.4.1.dist-info/licenses/LICENSE
runweb/__init__.py
runweb/__main__.py
runweb/__version__.py
runweb/logging.py
runweb/main.py
runweb/multiprocess.py
runweb/parse.py
runweb/runner/__init__.py
runweb/runner/uvicorn.py
runweb/runner/waitress.py
runweb-0.4.1.dist-info/RECORD
